[{"Name":"Global Top 50","Playlist_Id":"37i9dQZEVXbMDoHDwVN2tF","Country":"Global"},{"Name":"Argentina Top 50","Playlist_Id":"37i9dQZEVXbMMy2roB9myp","Country":"Argentina"},{"Name":"Australia Top 50","Playlist_Id":"37i9dQZEVXbJPcfkRz0wJ0","Country":"Australia"},{"Name":"Belgium Top 50","Playlist_Id":"37i9dQZEVXbJNSeeHswcKB","Country":"Belgium"},{"Name":"Bolivia Top 50","Playlist_Id":"37i9dQZEVXbJqfMFK4d691","Country":"Bolivia"},{"Name":"Brazil Top 50","Playlist_Id":"37i9dQZEVXbMXbN3EUUhlg","Country":"Brazil"},{"Name":"Bulgaria Top 50","Playlist_Id":"37i9dQZEVXbNfM2w2mq1B8","Country":"Bulgaria"},{"Name":"Chile Top 50","Playlist_Id":"37i9dQZEVXbL0GavIqMTeb","Country":"Chile"},{"Name":"Costa Rica Top 50","Playlist_Id":"37i9dQZEVXbMZAjGMynsQX","Country":"Costa Rica"},{"Name":"Denmark Top 50","Playlist_Id":"37i9dQZEVXbL3J0k32lWnN","Country":"Denmark"},{"Name":"Germany Top 50","Playlist_Id":"37i9dQZEVXbJiZcmkrIHGU","Country":"Germany"},{"Name":"Dominican Republic Top 50","Playlist_Id":"37i9dQZEVXbKAbrMR8uuf7","Country":"Dominican Republic"},{"Name":"Ecuador Top 50","Playlist_Id":"37i9dQZEVXbJlM6nvL1nD1","Country":"Ecuador"},{"Name":"El Salvador Top 50","Playlist_Id":"37i9dQZEVXbLxoIml4MYkT","Country":"El Salvador"},{"Name":"Estonia Top 50","Playlist_Id":"37i9dQZEVXbLesry2Qw2xS","Country":"Estonia"},{"Name":"Finland Top 50","Playlist_Id":"37i9dQZEVXbMxcczTSoGwZ","Country":"Finland"},{"Name":"France Top 50","Playlist_Id":"37i9dQZEVXbIPWwFssbupI","Country":"France"},{"Name":"Greece Top 50","Playlist_Id":"37i9dQZEVXbJqdarpmTJDL","Country":"Greece"},{"Name":"Guatemala Top 50","Playlist_Id":"37i9dQZEVXbLy5tBFyQvd4","Country":"Guatemala"},{"Name":"Honduras Top 50","Playlist_Id":"37i9dQZEVXbJp9wcIM9Eo5","Country":"Honduras"},{"Name":"India Top 50","Playlist_Id":"37i9dQZEVXbLZ52XmnySJg","Country":"India"},{"Name":"Indonesia Top 50","Playlist_Id":"37i9dQZEVXbObFQZ3JLcXt","Country":"Indonesia"},{"Name":"Ireland Top 50","Playlist_Id":"37i9dQZEVXbKM896FDX8L1","Country":"Ireland"},{"Name":"Iceland Top 50","Playlist_Id":"37i9dQZEVXbKMzVsSGQ49S","Country":"Iceland"},{"Name":"Israel Top 50","Playlist_Id":"37i9dQZEVXbJ6IpvItkve3","Country":"Israel"},{"Name":"Italy Top 50","Playlist_Id":"37i9dQZEVXbIQnj7RRhdSX","Country":"Italy"},{"Name":"Japan Top 50","Playlist_Id":"37i9dQZEVXbKXQ4mDTEBXq","Country":"Japan"},{"Name":"Canada Top 50","Playlist_Id":"37i9dQZEVXbKj23U1GF4IR","Country":"Canada"},{"Name":"Colombia Top 50","Playlist_Id":"37i9dQZEVXbOa2lmxNORXQ","Country":"Colombia"},{"Name":"Latvia Top 50","Playlist_Id":"37i9dQZEVXbJWuzDrTxbKS","Country":"Latvia"},{"Name":"Lithuania Top 50","Playlist_Id":"37i9dQZEVXbMx56Rdq5lwc","Country":"Lithuania"},{"Name":"Luxembourg Top 50","Playlist_Id":"37i9dQZEVXbKGcyg6TFGx6","Country":"Luxembourg"},{"Name":"Malaysia Top 50","Playlist_Id":"37i9dQZEVXbJlfUljuZExa","Country":"Malaysia"},{"Name":"Mexico Top 50","Playlist_Id":"37i9dQZEVXbO3qyFxbkOE1","Country":"Mexico"},{"Name":"New Zealand Top 50","Playlist_Id":"37i9dQZEVXbM8SIrkERIYl","Country":"New Zealand"},{"Name":"Nicaragua Top 50","Playlist_Id":"37i9dQZEVXbISk8kxnzfCq","Country":"Nicaragua"},{"Name":"Netherlands Top 50","Playlist_Id":"37i9dQZEVXbKCF6dqVpDkS","Country":"Netherlands"},{"Name":"Norway Top 50","Playlist_Id":"37i9dQZEVXbJvfa0Yxg7E7","Country":"Norway"},{"Name":"Austria Top 50","Playlist_Id":"37i9dQZEVXbKNHh6NIXu36","Country":"Austria"},{"Name":"Panama Top 50","Playlist_Id":"37i9dQZEVXbKypXHVwk1f0","Country":"Panama"},{"Name":"Paraguay Top 50","Playlist_Id":"37i9dQZEVXbNOUPGj7tW6T","Country":"Paraguay"},{"Name":"Peru Top 50","Playlist_Id":"37i9dQZEVXbJfdy5b0KP7W","Country":"Peru"},{"Name":"Philippines Top 50","Playlist_Id":"37i9dQZEVXbNBz9cRCSFkY","Country":"Philippines"},{"Name":"Poland Top 50","Playlist_Id":"37i9dQZEVXbN6itCcaL3Tt","Country":"Poland"},{"Name":"Portugal Top 50","Playlist_Id":"37i9dQZEVXbKyJS56d1pgi","Country":"Portugal"},{"Name":"Romania Top 50","Playlist_Id":"37i9dQZEVXbNZbJ6TZelCq","Country":"Romania"},{"Name":"Sweden Top 50","Playlist_Id":"37i9dQZEVXbLoATJ81JYXz","Country":"Sweden"},{"Name":"Switzerland Top 50","Playlist_Id":"37i9dQZEVXbJiyhoAPEfMK","Country":"Switzerland"},{"Name":"Singapore Top 50","Playlist_Id":"37i9dQZEVXbK4gjvS1FjPY","Country":"Singapore"},{"Name":"Slovakia Top 50","Playlist_Id":"37i9dQZEVXbKIVTPX9a2Sb","Country":"Slovakia"},{"Name":"Hong Kong Top 50","Playlist_Id":"37i9dQZEVXbLwpL8TjsxOG","Country":"Hong Kong"},{"Name":"Spain Top 50","Playlist_Id":"37i9dQZEVXbNFJfN1Vw8d9","Country":"Spain"},{"Name":"South Africa Top 50","Playlist_Id":"37i9dQZEVXbMH2jvi6jvjk","Country":"South Africa"},{"Name":"Taiwan Top 50","Playlist_Id":"37i9dQZEVXbMnZEatlMSiu","Country":"Taiwan"},{"Name":"Thailand Top 50","Playlist_Id":"37i9dQZEVXbMnz8KIWsvf9","Country":"Thailand"},{"Name":"Czech Republic Top 50","Playlist_Id":"37i9dQZEVXbIP3c3fqVrJY","Country":"Czech Republic"},{"Name":"Turkey Top 50","Playlist_Id":"37i9dQZEVXbIVYVBNw9D5K","Country":"Turkey"},{"Name":"Hungary Top 50","Playlist_Id":"37i9dQZEVXbNHwMxAkvmF8","Country":"Hungary"},{"Name":"Uruguay Top 50","Playlist_Id":"37i9dQZEVXbMJJi3wgRbAy","Country":"Uruguay"},{"Name":"United Kingdom Top 50","Playlist_Id":"37i9dQZEVXbLnolsZ8PSNw","Country":"United Kingdom"},{"Name":"United States Top 50","Playlist_Id":"37i9dQZEVXbLRQDuF5jeBp","Country":"United States"},{"Name":"Vietnam Top 50","Playlist_Id":"37i9dQZEVXbLdGSmz6xilI","Country":"Vietnam"}]